podcastindex/__init__.py
podcastindex/podcastindex.py
python_podcastindex-1.13.0.dist-info/LICENSE
python_podcastindex-1.13.0.dist-info/METADATA
python_podcastindex-1.13.0.dist-info/WHEEL
python_podcastindex-1.13.0.dist-info/entry_points.txt
python_podcastindex-1.13.0.dist-info/top_level.txt
python_podcastindex-1.13.0.dist-info/RECORD
