Metadata-Version: 2.1
Name: python-podcastindex
Version: 1.13.0
Summary: A python wrapper for the Podcast Index API (podcastindex.org).
Home-page: https://github.com/SarvagyaVaish/python-podcastindex
Author: Sarvagya (Survy) Vaish
Author-email: sarvagya.vaish7@gmail.com
Classifier: License :: OSI Approved :: MIT License
Classifier: Programming Language :: Python :: 2.7
Classifier: Programming Language :: Python :: 3
Classifier: Programming Language :: Python :: 3.4
Classifier: Programming Language :: Python :: 3.5
Classifier: Programming Language :: Python :: 3.6
Classifier: Programming Language :: Python :: 3.7
Requires-Python: >=2.7
License-File: LICENSE
Requires-Dist: requests
